MANIFEST.in
README.mkdn
setup.py
tomber/__init__.py
tomber/test.jpg
tomber/test.py
tomber/tomber.py
tomber.egg-info/PKG-INFO
tomber.egg-info/SOURCES.txt
tomber.egg-info/dependency_links.txt
tomber.egg-info/top_level.txt
tomber/tools/__init__.py
tomber/tools/parser.py