Metadata-Version: 1.0
Name: tomber
Version: 1.0.4
Summary: a python Tomb (the Crypto Undertaker) wrapper
Home-page: https://github.com/reiven/tomber
Author: Federico Reiven
Author-email: reiven@gmail.com
License: BSD
Keywords: tomb wrapper
Platform: UNKNOWN
